opentelemetry/instrumentation/elasticsearch/__init__.py
opentelemetry/instrumentation/elasticsearch/package.py
opentelemetry/instrumentation/elasticsearch/utils.py
opentelemetry/instrumentation/elasticsearch/version.py
odigos_opentelemetry_instrumentation_elasticsearch-0.52b1.dist-info/METADATA
odigos_opentelemetry_instrumentation_elasticsearch-0.52b1.dist-info/WHEEL
odigos_opentelemetry_instrumentation_elasticsearch-0.52b1.dist-info/entry_points.txt
odigos_opentelemetry_instrumentation_elasticsearch-0.52b1.dist-info/RECORD
